{
   "document" : {
      "category" : "csaf_informational_advisory",
      "csaf_version" : "2.0",
      "distribution" : {
         "tlp" : {
            "label" : "WHITE",
            "url" : "https://www.first.org/tlp/"
         }
      },
      "lang" : "en",
      "notes" : [
         {
            "category" : "description",
            "text" : "There was a potential security hole when outputting entities with recommended filenames.",
            "title" : "Vulnerability Description"
         }
      ],
      "publisher" : {
         "category" : "other",
         "contact_details" : "gdt@cpan.org",
         "name" : "giterlizzi",
         "namespace" : "https://github.com/giterlizzi/"
      },
      "references" : [
         {
            "category" : "self",
            "summary" : "CPANSA-MIME-tools-1998-01 JSON",
            "url" : "https://raw.githubusercontent.com/giterlizzi/perl-CPANSA-CSAF/develop/csaf/white/1998/cpansa-mime-tools-1998-01.json"
         },
         {
            "category" : "external",
            "summary" : "https://metacpan.org/dist/MIME-tools/changes",
            "url" : "https://metacpan.org/dist/MIME-tools/changes"
         }
      ],
      "title" : "MIME-tools vulnerability",
      "tracking" : {
         "current_release_date" : "1998-01-10T00:00:00",
         "generator" : {
            "engine" : {
               "name" : "CSAF Perl Toolkit",
               "version" : "0.24"
            }
         },
         "id" : "CPANSA-MIME-tools-1998-01",
         "initial_release_date" : "1998-01-10T00:00:00",
         "revision_history" : [
            {
               "date" : "1998-01-10T00:00:00",
               "number" : "1",
               "summary" : "First release"
            }
         ],
         "status" : "final",
         "version" : "1"
      }
   },
   "product_tree" : {
      "branches" : [
         {
            "branches" : [
               {
                  "category" : "product_version_range",
                  "name" : "vers:cpan/<4.109",
                  "product" : {
                     "name" : "MIME-tools less than 4.109",
                     "product_id" : "CSAFPID-0001",
                     "product_identification_helper" : {
                        "purl" : "pkg:cpan/MIME::Head"
                     }
                  }
               },
               {
                  "category" : "product_version_range",
                  "name" : "vers:cpan/>=4.109",
                  "product" : {
                     "name" : "MIME-tools greater than or equal 4.109",
                     "product_id" : "CSAFPID-0002",
                     "product_identification_helper" : {
                        "purl" : "pkg:cpan/MIME::Head"
                     }
                  }
               }
            ],
            "category" : "product_name",
            "name" : "MIME-tools"
         }
      ]
   }
}
